CHANGELOG
LICENSE
MANIFEST.in
README.rst
setup.py
mezzanine_wiki/__init__.py
mezzanine_wiki/admin.py
mezzanine_wiki/defaults.py
mezzanine_wiki/fields.py
mezzanine_wiki/filters.py
mezzanine_wiki/forms.py
mezzanine_wiki/managers.py
mezzanine_wiki/mdx_wikilinks_extra.py
mezzanine_wiki/models.py
mezzanine_wiki/urls.py
mezzanine_wiki/utils.py
mezzanine_wiki/views.py
mezzanine_wiki.egg-info/PKG-INFO
mezzanine_wiki.egg-info/SOURCES.txt
mezzanine_wiki.egg-info/dependency_links.txt
mezzanine_wiki.egg-info/entry_points.txt
mezzanine_wiki.egg-info/not-zip-safe
mezzanine_wiki.egg-info/requires.txt
mezzanine_wiki.egg-info/top_level.txt
mezzanine_wiki/__pycache__/__init__.cpython-36.pyc
mezzanine_wiki/__pycache__/admin.cpython-36.pyc
mezzanine_wiki/__pycache__/defaults.cpython-36.pyc
mezzanine_wiki/__pycache__/fields.cpython-36.pyc
mezzanine_wiki/__pycache__/filters.cpython-36.pyc
mezzanine_wiki/__pycache__/forms.cpython-36.pyc
mezzanine_wiki/__pycache__/managers.cpython-36.pyc
mezzanine_wiki/__pycache__/mdx_wikilinks_extra.cpython-36.pyc
mezzanine_wiki/__pycache__/models.cpython-36.pyc
mezzanine_wiki/__pycache__/urls.cpython-36.pyc
mezzanine_wiki/__pycache__/utils.cpython-36.pyc
mezzanine_wiki/__pycache__/views.cpython-36.pyc
mezzanine_wiki/migrations/0001_initial.py
mezzanine_wiki/migrations/__init__.py
mezzanine_wiki/migrations/__pycache__/0001_initial.cpython-36.pyc
mezzanine_wiki/migrations/__pycache__/__init__.cpython-36.pyc
mezzanine_wiki/static/css/wiki.css
mezzanine_wiki/templates/mezawiki/wiki_page_changes.html
mezzanine_wiki/templates/mezawiki/wiki_page_detail.html
mezzanine_wiki/templates/mezawiki/wiki_page_diff.html
mezzanine_wiki/templates/mezawiki/wiki_page_edit.html
mezzanine_wiki/templates/mezawiki/wiki_page_history.html
mezzanine_wiki/templates/mezawiki/wiki_page_list.html
mezzanine_wiki/templates/mezawiki/wiki_page_new.html
mezzanine_wiki/templates/mezawiki/wiki_page_revision.html
mezzanine_wiki/templates/mezawiki/includes/filter_panel.html
mezzanine_wiki/templatetags/__init__.py
mezzanine_wiki/templatetags/mezawiki_tags.py
mezzanine_wiki/templatetags/__pycache__/__init__.cpython-36.pyc
mezzanine_wiki/templatetags/__pycache__/mezawiki_tags.cpython-36.pyc